scikit_lego-0.9.7.dist-info/licenses/LICENSE
sklego/__init__.py
sklego/base.py
sklego/common.py
sklego/datasets.py
sklego/dummy.py
sklego/linear_model.py
sklego/metrics.py
sklego/model_selection.py
sklego/naive_bayes.py
sklego/neighbors.py
sklego/notinstalled.py
sklego/pandas_utils.py
sklego/pipeline.py
sklego/testing.py
sklego/this.py
sklego/data/abalone.zip
sklego/data/arrests.zip
sklego/data/chickweight.zip
sklego/data/hearts.zip
sklego/data/heroes.zip
sklego/data/penguins.zip
sklego/decomposition/__init__.py
sklego/decomposition/pca_reconstruction.py
sklego/decomposition/umap_reconstruction.py
sklego/feature_selection/__init__.py
sklego/feature_selection/mrmr.py
sklego/meta/__init__.py
sklego/meta/_decay_utils.py
sklego/meta/_grouped_utils.py
sklego/meta/_shrinkage_utils.py
sklego/meta/confusion_balancer.py
sklego/meta/decay_estimator.py
sklego/meta/estimator_transformer.py
sklego/meta/grouped_predictor.py
sklego/meta/grouped_transformer.py
sklego/meta/hierarchical_predictor.py
sklego/meta/ordinal_classification.py
sklego/meta/outlier_classifier.py
sklego/meta/regression_outlier_detector.py
sklego/meta/subjective_classifier.py
sklego/meta/thresholder.py
sklego/meta/zero_inflated_regressor.py
sklego/mixture/__init__.py
sklego/mixture/bayesian_gmm_classifier.py
sklego/mixture/bayesian_gmm_detector.py
sklego/mixture/gmm_classifier.py
sklego/mixture/gmm_outlier_detector.py
sklego/preprocessing/__init__.py
sklego/preprocessing/columncapper.py
sklego/preprocessing/dictmapper.py
sklego/preprocessing/formulaictransformer.py
sklego/preprocessing/identitytransformer.py
sklego/preprocessing/intervalencoder.py
sklego/preprocessing/linearembedder.py
sklego/preprocessing/monotonicspline.py
sklego/preprocessing/outlier_remover.py
sklego/preprocessing/pandastransformers.py
sklego/preprocessing/projections.py
sklego/preprocessing/randomadder.py
sklego/preprocessing/repeatingbasis.py
scikit_lego-0.9.7.dist-info/METADATA
scikit_lego-0.9.7.dist-info/WHEEL
scikit_lego-0.9.7.dist-info/top_level.txt
scikit_lego-0.9.7.dist-info/RECORD
